appwrite_typing/__init__.py
appwrite_typing/py310/__init__.py
appwrite_typing/py310/server.py
appwrite_typing/py311/__init__.py
appwrite_typing/py311/server.py
appwrite_typing/py312/__init__.py
appwrite_typing/py312/server.py
appwrite_typing/py38/__init__.py
appwrite_typing/py38/server.py
appwrite_typing/py39/__init__.py
appwrite_typing/py39/server.py
appwrite_typing-0.0.dist-info/METADATA
appwrite_typing-0.0.dist-info/WHEEL
appwrite_typing-0.0.dist-info/top_level.txt
appwrite_typing-0.0.dist-info/RECORD
