Metadata-Version: 2.1
Name: appwrite-typing
Version: 0.0
Summary: Type hints for Appwrite Python SDK
Home-page: https://github.com/yourusername/mypackage
Author: Bas Krahmer
Classifier: Programming Language :: Python :: 3
Classifier: License :: OSI Approved :: MIT License
Classifier: Operating System :: OS Independent
Requires-Dist: Flask
